GSCAP/__init__.py
GSCAP/gps.py
GSCAP/utils.py
GSCAP/weather.py
gscapl/__init__.py
gscapl/gps.py
gscapl/utils.py
gscapl/weather.py
gscep/__init__.py
gscep/gps.py
gscep/utils.py
gscep/weather.py
gscp/__init__.py
gscp/gps.py
gscp/utils.py
gscp/weather.py
gscapl-0.0.0.5.dist-info/LICENSE
gscapl-0.0.0.5.dist-info/METADATA
gscapl-0.0.0.5.dist-info/WHEEL
gscapl-0.0.0.5.dist-info/top_level.txt
gscapl-0.0.0.5.dist-info/RECORD
